Metadata-Version: 1.0
Name: dist-udacity-dh
Version: 0.1
Summary: Gaussian and Binomial distributions
Home-page: UNKNOWN
Author: Daria HERVIEUX
Author-email: UNKNOWN
License: UNKNOWN
Platform: UNKNOWN
